llama_index/readers/azstorage_blob/__init__.py
llama_index/readers/azstorage_blob/base.py
llama_index_readers_azstorage_blob-0.4.1.dist-info/METADATA
llama_index_readers_azstorage_blob-0.4.1.dist-info/WHEEL
llama_index_readers_azstorage_blob-0.4.1.dist-info/licenses/LICENSE
llama_index_readers_azstorage_blob-0.4.1.dist-info/RECORD
