Metadata-Version: 2.4
Name: llama-index-readers-azstorage-blob
Version: 0.4.1
Summary: llama-index readers azstorage_blob integration
Author-email: Your Name <you@example.com>
Maintainer: rivms
License-Expression: MIT
License-File: LICENSE
Keywords: azure,azure storage,blob,container
Requires-Python: <4.0,>=3.9
Requires-Dist: azure-identity<2,>=1.15.0
Requires-Dist: azure-storage-blob<13,>=12.19.0
Requires-Dist: llama-index-core<0.15,>=0.13.0
